actimai_genix-1.0.0.dist-info/licenses/LICENSE
genix/__init__.py
genix/main.py
genix/sender.py
actimai_genix-1.0.0.dist-info/METADATA
actimai_genix-1.0.0.dist-info/WHEEL
actimai_genix-1.0.0.dist-info/top_level.txt
actimai_genix-1.0.0.dist-info/RECORD
